pyradios/__init__.py
pyradios/base_url.py
pyradios/facets.py
pyradios/radios.py
pyradios/utils.py
pyradios-2.1.0.dist-info/LICENSE
pyradios-2.1.0.dist-info/METADATA
pyradios-2.1.0.dist-info/WHEEL
pyradios-2.1.0.dist-info/top_level.txt
pyradios-2.1.0.dist-info/RECORD
