Metadata-Version: 2.1
Name: pyradios
Version: 2.1.0
Summary: Python client for the Radio Browser API
Home-page: https://github.com/andreztz/pyradios
Author: André P. Santos
Author-email: andreztz@gmail.com
License: MIT
Project-URL: Source, https://github.com/andreztz/pyradios/
Project-URL: Upstream, https://api.radio-browser.info/
Keywords: pyradios wrapper radios api
Classifier: Development Status :: 1 - Planning
Classifier: Environment :: Console
Classifier: Programming Language :: Python :: 3
Classifier: Operating System :: OS Independent
Classifier: Intended Audience :: Developers
Requires-Python: >=3.6
License-File: LICENSE
Requires-Dist: httpx >=0.25.2
Provides-Extra: dev
Requires-Dist: pytest >=6.2.5 ; extra == 'dev'
Requires-Dist: flake8 >=4.0.1 ; extra == 'dev'
Requires-Dist: setuptools ; extra == 'dev'
Requires-Dist: pytest-recording ; extra == 'dev'
Requires-Dist: pytest-mock ; extra == 'dev'
